apiloc/__init__.py
apiloc/apiloc.py
apiloc-0.2.0.dist-info/METADATA
apiloc-0.2.0.dist-info/WHEEL
apiloc-0.2.0.dist-info/top_level.txt
apiloc-0.2.0.dist-info/RECORD
