Metadata-Version: 2.1
Name: apiloc
Version: 0.2.0
Summary: A simple Flask API to manage items
Author: Baskar
Author-email: newtonbaskar@example.com
Classifier: Programming Language :: Python :: 3
Classifier: License :: OSI Approved :: MIT License
Classifier: Operating System :: OS Independent
Requires-Python: >=3.6
Requires-Dist: Flask
